s3urls.py
s3urls-0.0.3.dist-info/METADATA
s3urls-0.0.3.dist-info/RECORD
s3urls-0.0.3.dist-info/WHEEL
s3urls-0.0.3.dist-info/top_level.txt
