Metadata-Version: 2.1
Name: s3urls
Version: 0.0.3
Summary: Parse and build Amazon S3 URLs
Home-page: https://github.com/ButoVideo/s3urls
Author: Ben Steadman
Author-email: steadmanben1@gmail.com
License: MIT
Platform: UNKNOWN
Classifier: Programming Language :: Python :: 3.6
Classifier: License :: OSI Approved :: MIT License
Classifier: Operating System :: OS Independent
Classifier: Topic :: Utilities
Requires-Python: >=3.6.0
